cron_expression_generator/__init__.py
cron_expression_generator/generator.py
cron_expression_generator-0.0.1.dist-info/LICENSE
cron_expression_generator-0.0.1.dist-info/METADATA
cron_expression_generator-0.0.1.dist-info/WHEEL
cron_expression_generator-0.0.1.dist-info/top_level.txt
cron_expression_generator-0.0.1.dist-info/RECORD
