Metadata-Version: 2.1
Name: cron_expression_generator
Version: 0.0.1
Summary: Generates cron expression for cron job scheduling
Author-email: Shadrach Oforkansi <oforkansi.shadrach@gmail.com>
Project-URL: Homepage, https://github.com/o4codes/cron_expression_generator
Project-URL: Issues, https://github.com/o4codes/cron_expression_generator/issues
Classifier: Programming Language :: Python :: 3
Classifier: License :: OSI Approved :: MIT License
Classifier: Operating System :: OS Independent
Requires-Python: >=3.8
License-File: LICENSE
